card_games/__init__.py
card_games/blackjack/README.md
card_games/blackjack/__init__.py
card_games/blackjack/__main__.py
card_games/blackjack/cli.py
card_games/blackjack/educational.py
card_games/blackjack/game.py
card_games/blackjack/gui.py
card_games/blackjack/gui_pyqt.py
card_games/bluff/README.md
card_games/bluff/__init__.py
card_games/bluff/__main__.py
card_games/bluff/bluff.py
card_games/bluff/gui.py
card_games/bluff/gui_pyqt.py
card_games/bridge/README.md
card_games/bridge/__init__.py
card_games/bridge/__main__.py
card_games/bridge/bidding.py
card_games/bridge/cli.py
card_games/bridge/game.py
card_games/bridge/gui.py
card_games/bridge/gui_pyqt.py
card_games/canasta/README.md
card_games/canasta/__init__.py
card_games/canasta/__main__.py
card_games/canasta/cli.py
card_games/canasta/game.py
card_games/canasta/gui.py
card_games/canasta/gui_pyqt.py
card_games/common/__init__.py
card_games/common/cards.py
card_games/common/soundscapes.py
card_games/common/stats.py
card_games/crazy_eights/README.md
card_games/crazy_eights/__init__.py
card_games/crazy_eights/__main__.py
card_games/crazy_eights/cli.py
card_games/crazy_eights/game.py
card_games/crazy_eights/gui.py
card_games/crazy_eights/gui_pyqt.py
card_games/cribbage/README.md
card_games/cribbage/__init__.py
card_games/cribbage/__main__.py
card_games/cribbage/ai.py
card_games/cribbage/cli.py
card_games/cribbage/game.py
card_games/euchre/README.md
card_games/euchre/__init__.py
card_games/euchre/__main__.py
card_games/euchre/ai.py
card_games/euchre/cli.py
card_games/euchre/game.py
card_games/gin_rummy/README.md
card_games/gin_rummy/__init__.py
card_games/gin_rummy/__main__.py
card_games/gin_rummy/cli.py
card_games/gin_rummy/game.py
card_games/gin_rummy/gui.py
card_games/gin_rummy/gui_pyqt.py
card_games/go_fish/README.md
card_games/go_fish/__init__.py
card_games/go_fish/__main__.py
card_games/go_fish/cli.py
card_games/go_fish/game.py
card_games/go_fish/gui.py
card_games/go_fish/gui_pyqt.py
card_games/hearts/README.md
games_collection-1.6.1.dist-info/licenses/LICENSE
games_collection-1.6.1.dist-info/METADATA
games_collection-1.6.1.dist-info/WHEEL
games_collection-1.6.1.dist-info/entry_points.txt
games_collection-1.6.1.dist-info/top_level.txt
games_collection-1.6.1.dist-info/RECORD
