Metadata-Version: 2.4
Name: games-collection
Version: 1.6.1
Summary: A comprehensive collection of classic card, paper, dice, logic, and word games with AI opponents and both CLI and GUI interfaces
Author-email: saint2706 <45678566+saint2706@users.noreply.github.com>
Maintainer-email: saint2706 <45678566+saint2706@users.noreply.github.com>
License: MIT
Project-URL: Homepage, https://github.com/saint2706/Games
Project-URL: Documentation, https://github.com/saint2706/Games#readme
Project-URL: Repository, https://github.com/saint2706/Games
Project-URL: Issues, https://github.com/saint2706/Games/issues
Project-URL: Changelog, https://github.com/saint2706/Games/blob/master/CHANGELOG.md
Keywords: games,card-games,board-games,uno,poker,blackjack,tic-tac-toe,chess,ai,gui,cli
Classifier: Development Status :: 4 - Beta
Classifier: Intended Audience :: End Users/Desktop
Classifier: Intended Audience :: Developers
Classifier: License :: OSI Approved :: MIT License
Classifier: Operating System :: OS Independent
Classifier: Programming Language :: Python :: 3
Classifier: Programming Language :: Python :: 3.9
Classifier: Programming Language :: Python :: 3.10
Classifier: Programming Language :: Python :: 3.11
Classifier: Programming Language :: Python :: 3.12
Classifier: Topic :: Games/Entertainment
Classifier: Topic :: Games/Entertainment :: Board Games
Classifier: Topic :: Games/Entertainment :: Puzzle Games
Classifier: Topic :: Software Development :: Libraries :: Python Modules
Requires-Python: >=3.9
License-File: LICENSE
Requires-Dist: colorama>=0.4.6
Provides-Extra: dev
Requires-Dist: pytest>=7.0.0; extra == "dev"
Requires-Dist: pytest-cov>=4.0.0; extra == "dev"
Requires-Dist: pytest-xdist>=3.0.0; extra == "dev"
Requires-Dist: pytest-timeout>=2.1.0; extra == "dev"
Requires-Dist: pytest-qt>=4.0.0; extra == "dev"
Requires-Dist: pyqt5; extra == "dev"
Requires-Dist: pytest-benchmark>=4.0.0; extra == "dev"
Requires-Dist: black>=24.0; extra == "dev"
Requires-Dist: ruff>=0.8; extra == "dev"
Requires-Dist: mdformat>=0.7.0; extra == "dev"
Requires-Dist: mypy>=1.0; extra == "dev"
Requires-Dist: pre-commit>=3.0; extra == "dev"
Requires-Dist: radon>=6.0; extra == "dev"
Requires-Dist: coverage[toml]>=7.0.0; extra == "dev"
Requires-Dist: mutmut>=2.4.0; extra == "dev"
Requires-Dist: freezegun>=1.2.0; extra == "dev"
Requires-Dist: responses>=0.23.0; extra == "dev"
Requires-Dist: pytest-mock>=3.10.0; extra == "dev"
Provides-Extra: gui
Requires-Dist: pyqt5>=5.15; extra == "gui"
Requires-Dist: pygame>=2.0; extra == "gui"
Dynamic: license-file
